InternetSpeedVisualizer/InternetSpeedVisualizer.py
InternetSpeedVisualizer/__init__.py
InternetSpeedVisualizer-1.1.0.dist-info/LICENSE
InternetSpeedVisualizer-1.1.0.dist-info/METADATA
InternetSpeedVisualizer-1.1.0.dist-info/WHEEL
InternetSpeedVisualizer-1.1.0.dist-info/entry_points.txt
InternetSpeedVisualizer-1.1.0.dist-info/top_level.txt
InternetSpeedVisualizer-1.1.0.dist-info/RECORD
