Metadata-Version: 2.1
Name: InternetSpeedVisualizer
Version: 1.1.0
Summary: InternetSpeedVisualizer is a powerful tool designed to help you visualize and analyze your Internet speed data, collected using the InternetSpeedLogger. 
Author-email: Andreas Menzel <mail@andreas-menzel.com>
License: MIT License
Project-URL: Repository, https://github.com/Andreas-Menzel/InternetSpeedVisualizer
Project-URL: Bug Tracker, https://github.com/Andreas-Menzel/InternetSpeedVisualizer/issues
Keywords: speedtest,speedtest_cli,internet,internet speed,logger,monitor,visualizer,visualize
Classifier: Programming Language :: Python :: 3
Classifier: License :: OSI Approved :: MIT License
Classifier: Operating System :: OS Independent
Requires-Python: >=3.6
License-File: LICENSE
Requires-Dist: matplotlib
Requires-Dist: pandas
